fav_plots/__init__.py
fav_plots/bars.py
fav_plots/box.py
fav_plots/lines.py
fav_plots/utils.py
fav_plots-0.0.6.dist-info/LICENSE
fav_plots-0.0.6.dist-info/METADATA
fav_plots-0.0.6.dist-info/WHEEL
fav_plots-0.0.6.dist-info/top_level.txt
fav_plots-0.0.6.dist-info/RECORD
