Metadata-Version: 2.1
Name: fav-plots
Version: 0.0.6
Summary: package to make some favourite plots
Author-email: Mena Wang <ningwang25@gmail.com>
Project-URL: Homepage, https://github.com/MenaWANG/fav_plots
Classifier: Programming Language :: Python :: 3
Classifier: License :: OSI Approved :: MIT License
Classifier: Operating System :: OS Independent
Requires-Python: >=3.10
License-File: LICENSE
Requires-Dist: plotnine >=0.10.0
